spykus/__init__.py
spykus/__main__.py
spykus/install_windows.py
spykus/core/__init__.py
spykus/core/ast.py
spykus/core/interpreter.py
spykus/core/lexer.py
spykus/core/parser.py
spykus/core/utils.py
spykus-1.0.1.dist-info/METADATA
spykus-1.0.1.dist-info/WHEEL
spykus-1.0.1.dist-info/entry_points.txt
spykus-1.0.1.dist-info/top_level.txt
spykus-1.0.1.dist-info/RECORD
