Metadata-Version: 2.4
Name: spykus
Version: 1.0.1
Summary: Interpreter of SpykusScript
Author: Conteek
License: MIT
Classifier: Programming Language :: Python :: 3
Classifier: License :: OSI Approved :: MIT License
Classifier: Operating System :: OS Independent
Requires-Python: >=3.7
Requires-Dist: pygame
Requires-Dist: requests
